slicednormals/HyperEllipse.py
slicednormals/SlicedNormals.py
slicednormals/Test.py
slicednormals/__init__.py
slicednormals/hyper_ellipse.py
slicednormals/sliced_normals.py
slicednormals-0.1.15a0.dist-info/LICENSE.txt
slicednormals-0.1.15a0.dist-info/METADATA
slicednormals-0.1.15a0.dist-info/WHEEL
slicednormals-0.1.15a0.dist-info/top_level.txt
slicednormals-0.1.15a0.dist-info/RECORD
