Metadata-Version: 2.1
Name: slicednormals
Version: 0.1.15a0
Summary: Library for fitting basic and scaled sliced normal distributions
Home-page: https://github.com/Institute-for-Risk-and-Uncertainty/Sliced-Normals-Python
Author: Alexander Wimbush
Author-email: alexanderpwimbush@gmail.com
License: gpl-3.0
Download-URL: https://github.com/Institute-for-Risk-and-Uncertainty/Sliced-Normals-Python/archive/0.1.15-alpha.tar.gz
Keywords: dependence,expansion,density
Platform: UNKNOWN
Requires-Dist: numpy
Requires-Dist: scipy
